.testr.conf
AUTHORS
ChangeLog
LICENSE
MANIFEST.in
README.rst
openstack-common.conf
requirements.txt
setup.cfg
setup.py
test-requirements.txt
tox.ini
doc/.gitignore
doc/Makefile
doc/source/conf.py
doc/source/index.rst
murano_common.egg-info/PKG-INFO
murano_common.egg-info/SOURCES.txt
murano_common.egg-info/dependency_links.txt
murano_common.egg-info/not-zip-safe
murano_common.egg-info/requires.txt
murano_common.egg-info/top_level.txt
muranocommon/__init__.py
muranocommon/helpers/__init__.py
muranocommon/helpers/token_sanitizer.py
muranocommon/messaging/__init__.py
muranocommon/messaging/message.py
muranocommon/messaging/mqclient.py
muranocommon/messaging/subscription.py
muranocommon/tests/__init__.py
muranocommon/tests/helpers/__init__.py
muranocommon/tests/helpers/token_sanitizer_tests.py
tools/install_venv.py
tools/install_venv_common.py
tools/with_venv.sh