Metadata-Version: 1.1
Name: murano-common
Version: 0.2.11
Summary: Shared library for Murano
Home-page: htts://launchpad.net/murano
Author: Mirantis, Inc.
Author-email: murano-all@lists.openstack.org
License: Apache License, Version 2.0
Platform: UNKNOWN
Classifier: Development Status :: 5 - Production/Stable
Classifier: Environment :: OpenStack
Classifier: Intended Audience :: Developers
Classifier: Intended Audience :: Information Technology
Classifier: License :: OSI Approved :: Apache Software License
Classifier: Operating System :: OS Independent
Classifier: Programming Language :: Python
